stateset_acp/__init__.py
stateset_acp/grpc_client.py
stateset_acp/http_client.py
stateset_acp/types.py
stateset_acp/proto/__init__.py
stateset_acp/proto/acp_handler.proto
stateset_acp-1.0.0.dist-info/METADATA
stateset_acp-1.0.0.dist-info/WHEEL
stateset_acp-1.0.0.dist-info/top_level.txt
stateset_acp-1.0.0.dist-info/RECORD
