Metadata-Version: 2.4
Name: stateset-acp
Version: 1.0.0
Summary: Python client for StateSet Agentic Commerce Protocol Handler
Author-email: StateSet <support@stateset.io>
License: MIT
Project-URL: Homepage, https://github.com/stateset/stateset-acp-handler
Project-URL: Documentation, https://github.com/stateset/stateset-acp-handler#readme
Project-URL: Repository, https://github.com/stateset/stateset-acp-handler
Keywords: stateset,acp,agentic-commerce,checkout,grpc,openai
Classifier: Development Status :: 4 - Beta
Classifier: Intended Audience :: Developers
Classifier: License :: OSI Approved :: MIT License
Classifier: Programming Language :: Python :: 3
Classifier: Programming Language :: Python :: 3.9
Classifier: Programming Language :: Python :: 3.10
Classifier: Programming Language :: Python :: 3.11
Classifier: Programming Language :: Python :: 3.12
Classifier: Topic :: Software Development :: Libraries :: Python Modules
Requires-Python: >=3.9
Requires-Dist: httpx>=0.25.0
Requires-Dist: grpcio>=1.60.0
Requires-Dist: grpcio-tools>=1.60.0
Requires-Dist: protobuf>=4.25.0
Requires-Dist: pydantic>=2.5.0
Provides-Extra: dev
Requires-Dist: pytest>=7.4.0; extra == "dev"
Requires-Dist: pytest-asyncio>=0.21.0; extra == "dev"
Requires-Dist: black>=23.0.0; extra == "dev"
Requires-Dist: mypy>=1.7.0; extra == "dev"
Requires-Dist: ruff>=0.1.0; extra == "dev"
